parzen_estimator/__init__.py
parzen_estimator/constants.py
parzen_estimator/loglikelihoods.py
parzen_estimator/multivar_parzen_estimator.py
parzen_estimator/parzen_estimator.py
parzen_estimator/uniform.py
parzen_estimator/utils.py
parzen_estimator-0.5.8.dist-info/LICENSE
parzen_estimator-0.5.8.dist-info/METADATA
parzen_estimator-0.5.8.dist-info/WHEEL
parzen_estimator-0.5.8.dist-info/top_level.txt
parzen_estimator-0.5.8.dist-info/RECORD
