Metadata-Version: 2.1
Name: parzen-estimator
Version: 0.5.8
Home-page: https://github.com/nabenabe0928/parzen_estimator
Author: nabenabe0928
Author-email: shuhei.watanabe.utokyo@gmail.com
Platform: Linux
Requires-Python: >=3.7
License-File: LICENSE
Requires-Dist: numpy
Requires-Dist: scipy
Requires-Dist: ConfigSpace
Requires-Dist: torch
